{
  "1": {
    "ID": 1,
    "Name": "Stage_Name_korea01",
    "ChapterID": 1,
    "NextStageID": 2,
    "ProbabilityGroupID": 1,
    "score1": 100,
    "score2": 200,
    "score3": 300,
    "StageFile": 0.0,
    "StagePrefab": "stage1-1",
    "StageTimer": 120,
    "StartRecipeValue": 2
  },
  "2": {
    "ID": 2,
    "Name": "Stage_Name_korea02",
    "ChapterID": 1,
    "NextStageID": 3,
    "ProbabilityGroupID": 2,
    "score1": 100,
    "score2": 200,
    "score3": 300,
    "StageFile": 0.0,
    "StagePrefab": "stage1-2",
    "StageTimer": 150,
    "StartRecipeValue": 2
  },
  "3": {
    "ID": 3,
    "Name": "Stage_Name_korea03",
    "ChapterID": 1,
    "NextStageID": 4,
    "ProbabilityGroupID": 3,
    "score1": 100,
    "score2": 200,
    "score3": 300,
    "StageFile": 0.0,
    "StagePrefab": "stage1-3",
    "StageTimer": 240,
    "StartRecipeValue": 3
  },
  "4": {
    "ID": 4,
    "Name": "Stage_Name_korea04",
    "ChapterID": 1,
    "NextStageID": 5,
    "ProbabilityGroupID": 4,
    "score1": 100,
    "score2": 200,
    "score3": 300,
    "StageFile": 0.0,
    "StagePrefab": "stage1-4",
    "StageTimer": 240,
    "StartRecipeValue": 4
  },
  "5": {
    "ID": 5,
    "Name": "Stage_Name_korea05",
    "ChapterID": 1,
    "NextStageID": 6,
    "ProbabilityGroupID": 5,
    "score1": 100,
    "score2": 200,
    "score3": 300,
    "StageFile": 0.0,
    "StagePrefab": "stage1-5",
    "StageTimer": 420,
    "StartRecipeValue": 4
  },
  "6": {
    "ID": 6,
    "Name": "Stage_Name_Usa01",
    "ChapterID": 2,
    "NextStageID": 7,
    "ProbabilityGroupID": 0,
    "score1": 100,
    "score2": 200,
    "score3": 300,
    "StageFile": 0.0,
    "StagePrefab": "stage2-1",
    "StageTimer": 210,
    "StartRecipeValue": 4
  },
  "7": {
    "ID": 7,
    "Name": "Stage_Name_Usa02",
    "ChapterID": 2,
    "NextStageID": 8,
    "ProbabilityGroupID": 0,
    "score1": 100,
    "score2": 200,
    "score3": 300,
    "StageFile": 0.0,
    "StagePrefab": "stage2-2",
    "StageTimer": 210,
    "StartRecipeValue": 4
  },
  "8": {
    "ID": 8,
    "Name": "Stage_Name_Usa03",
    "ChapterID": 2,
    "NextStageID": 9,
    "ProbabilityGroupID": 0,
    "score1": 100,
    "score2": 200,
    "score3": 300,
    "StageFile": 0.0,
    "StagePrefab": "stage2-3",
    "StageTimer": 210,
    "StartRecipeValue": 4
  },
  "9": {
    "ID": 9,
    "Name": "Stage_Name_Usa04",
    "ChapterID": 2,
    "NextStageID": 10,
    "ProbabilityGroupID": 0,
    "score1": 100,
    "score2": 200,
    "score3": 300,
    "StageFile": 0.0,
    "StagePrefab": "stage2-4",
    "StageTimer": 300,
    "StartRecipeValue": 4
  },
  "10": {
    "ID": 10,
    "Name": "Stage_Name_Usa05",
    "ChapterID": 2,
    "NextStageID": 0,
    "ProbabilityGroupID": 0,
    "score1": 100,
    "score2": 200,
    "score3": 300,
    "StageFile": 0.0,
    "StagePrefab": "stage2-5",
    "StageTimer": 420,
    "StartRecipeValue": 4
  }
}